nushell_sdk/__init__.py
nushell_sdk-0.0a1.dist-info/METADATA
nushell_sdk-0.0a1.dist-info/WHEEL
nushell_sdk-0.0a1.dist-info/licenses/LICENSE
nushell_sdk-0.0a1.dist-info/RECORD
