Metadata-Version: 2.1
Name: nushell-sdk
Version: 0.0a1
Summary: Nushell SDK to write Nushell plugins in Python easily
Project-URL: Homepage, https://github.com/presidento/nushell-python-sdk
Project-URL: Changelog, https://github.com/presidento/nushell-python-sdk/blob/main/CHANGELOG.md
Author-email: Máté Farkas <fm@farkas-mate.hu>
License: MIT License
License-File: LICENSE
Classifier: Development Status :: 3 - Alpha
Classifier: Intended Audience :: Developers
Classifier: Intended Audience :: System Administrators
Classifier: License :: OSI Approved :: MIT License
Classifier: Operating System :: OS Independent
Classifier: Programming Language :: Python :: 3 :: Only
Classifier: Topic :: Utilities
